gif_converter/__init__.py
gif_converter/gif_converter.py
gif_converter-0.1.1.dist-info/LICENSE
gif_converter-0.1.1.dist-info/METADATA
gif_converter-0.1.1.dist-info/WHEEL
gif_converter-0.1.1.dist-info/entry_points.txt
gif_converter-0.1.1.dist-info/top_level.txt
gif_converter-0.1.1.dist-info/RECORD
